[
    {
        "County": "Polk",
        "Precinct": "WDM-312",
        "First Expression": {
            "Bennet": 0,
            "Biden": 0,
            "Bloomberg": 0,
            "Buttigieg": 0,
            "Delaney": 0,
            "Gabbard": 0,
            "Klobuchar": 43,
            "Patrick": 0,
            "Sanders": 0,
            "Steyer": 0,
            "Warren": 0,
            "Yang": 18,
            "Other": 0,
            "Uncommitted": 0
        },
        "Final Expression": {
            "Bennet": 0,
            "Biden": 65,
            "Bloomberg": 0,
            "Buttigieg": 108,
            "Delaney": 0,
            "Gabbard": 0,
            "Klobuchar": 0,
            "Patrick": 0,
            "Sanders": 74,
            "Steyer": 0,
            "Warren": 92,
            "Yang": 0,
            "Other": 0,
            "Uncommitted": 0
        },
        "Final Vote Increase": 278
    },
    {
        "County": "Polk",
        "Precinct": "DES MOINES-80",
        "First Expression": {
            "Bennet": 0,
            "Biden": 0,
            "Bloomberg": 0,
            "Buttigieg": 0,
            "Delaney": 0,
            "Gabbard": 0,
            "Klobuchar": 0,
            "Patrick": 0,
            "Sanders": 0,
            "Steyer": 0,
            "Warren": 0,
            "Yang": 0,
            "Other": 0,
            "Uncommitted": 0
        },
        "Final Expression": {
            "Bennet": 0,
            "Biden": 48,
            "Bloomberg": 0,
            "Buttigieg": 66,
            "Delaney": 0,
            "Gabbard": 0,
            "Klobuchar": 0,
            "Patrick": 0,
            "Sanders": 101,
            "Steyer": 0,
            "Warren": 0,
            "Yang": 0,
            "Other": 0,
            "Uncommitted": 0
        },
        "Final Vote Increase": 215
    },
    {
        "County": "Polk",
        "Precinct": "URBANDALE-03",
        "First Expression": {
            "Bennet": 0,
            "Biden": 0,
            "Bloomberg": 0,
            "Buttigieg": 67,
            "Delaney": 0,
            "Gabbard": 0,
            "Klobuchar": 49,
            "Patrick": 0,
            "Sanders": 67,
            "Steyer": 0,
            "Warren": 65,
            "Yang": 0,
            "Other": 0,
            "Uncommitted": 0
        },
        "Final Expression": {
            "Bennet": 0,
            "Biden": 0,
            "Bloomberg": 0,
            "Buttigieg": 83,
            "Delaney": 0,
            "Gabbard": 0,
            "Klobuchar": 62,
            "Patrick": 0,
            "Sanders": 79,
            "Steyer": 0,
            "Warren": 81,
            "Yang": 0,
            "Other": 0,
            "Uncommitted": 0
        },
        "Final Vote Increase": 57
    },
    {
        "County": "Dallas",
        "Precinct": "WAUKEE 3",
        "First Expression": {
            "Bennet": 0,
            "Biden": 31,
            "Bloomberg": 0,
            "Buttigieg": 79,
            "Delaney": 0,
            "Gabbard": 0,
            "Klobuchar": 0,
            "Patrick": 0,
            "Sanders": 46,
            "Steyer": 0,
            "Warren": 45,
            "Yang": 0,
            "Other": 0,
            "Uncommitted": 3
        },
        "Final Expression": {
            "Bennet": 0,
            "Biden": 46,
            "Bloomberg": 0,
            "Buttigieg": 102,
            "Delaney": 0,
            "Gabbard": 0,
            "Klobuchar": 0,
            "Patrick": 0,
            "Sanders": 49,
            "Steyer": 0,
            "Warren": 57,
            "Yang": 0,
            "Other": 0,
            "Uncommitted": 0
        },
        "Final Vote Increase": 50
    },
    {
        "County": "Johnson",
        "Precinct": "IOWA CITY 23",
        "First Expression": {
            "Bennet": 1,
            "Biden": 73,
            "Bloomberg": 1,
            "Buttigieg": 115,
            "Delaney": 0,
            "Gabbard": 2,
            "Klobuchar": 90,
            "Patrick": 0,
            "Sanders": 172,
            "Steyer": 21,
            "Warren": 251,
            "Yang": 24,
            "Other": 0,
            "Uncommitted": 4
        },
        "Final Expression": {
            "Bennet": 0,
            "Biden": 0,
            "Bloomberg": 0,
            "Buttigieg": 147,
            "Delaney": 0,
            "Gabbard": 0,
            "Klobuchar": 80,
            "Patrick": 0,
            "Sanders": 192,
            "Steyer": 0,
            "Warren": 299,
            "Yang": 0,
            "Other": 0,
            "Uncommitted": 83
        },
        "Final Vote Increase": 47
    },
    {
        "County": "Dallas",
        "Precinct": "WAUKEE 5",
        "First Expression": {
            "Bennet": 0,
            "Biden": 42,
            "Bloomberg": 0,
            "Buttigieg": 95,
            "Delaney": 0,
            "Gabbard": 0,
            "Klobuchar": 14,
            "Patrick": 0,
            "Sanders": 24,
            "Steyer": 0,
            "Warren": 49,
            "Yang": 26,
            "Other": 1,
            "Uncommitted": 0
        },
        "Final Expression": {
            "Bennet": 0,
            "Biden": 51,
            "Bloomberg": 0,
            "Buttigieg": 117,
            "Delaney": 0,
            "Gabbard": 0,
            "Klobuchar": 14,
            "Patrick": 0,
            "Sanders": 24,
            "Steyer": 0,
            "Warren": 65,
            "Yang": 26,
            "Other": 0,
            "Uncommitted": 0
        },
        "Final Vote Increase": 46
    },
    {
        "County": "Webster",
        "Precinct": "Douglas",
        "First Expression": {
            "Bennet": 0,
            "Biden": 0,
            "Bloomberg": 0,
            "Buttigieg": 0,
            "Delaney": 0,
            "Gabbard": 0,
            "Klobuchar": 2,
            "Patrick": 0,
            "Sanders": 0,
            "Steyer": 3,
            "Warren": 3,
            "Yang": 0,
            "Other": 0,
            "Uncommitted": 0
        },
        "Final Expression": {
            "Bennet": 0,
            "Biden": 23,
            "Bloomberg": 0,
            "Buttigieg": 20,
            "Delaney": 0,
            "Gabbard": 0,
            "Klobuchar": 0,
            "Patrick": 0,
            "Sanders": 9,
            "Steyer": 0,
            "Warren": 0,
            "Yang": 0,
            "Other": 0,
            "Uncommitted": 0
        },
        "Final Vote Increase": 44
    },
    {
        "County": "Warren",
        "Precinct": "NORWALK 2/ GREENFIELD",
        "First Expression": {
            "Bennet": 0,
            "Biden": 0,
            "Bloomberg": 0,
            "Buttigieg": 35,
            "Delaney": 0,
            "Gabbard": 0,
            "Klobuchar": 23,
            "Patrick": 0,
            "Sanders": 25,
            "Steyer": 5,
            "Warren": 17,
            "Yang": 10,
            "Other": 0,
            "Uncommitted": 0
        },
        "Final Expression": {
            "Bennet": 0,
            "Biden": 12,
            "Bloomberg": 0,
            "Buttigieg": 55,
            "Delaney": 0,
            "Gabbard": 0,
            "Klobuchar": 34,
            "Patrick": 0,
            "Sanders": 32,
            "Steyer": 0,
            "Warren": 0,
            "Yang": 0,
            "Other": 0,
            "Uncommitted": 6
        },
        "Final Vote Increase": 24
    },
    {
        "County": "Dubuque",
        "Precinct": "Dubuque_43",
        "First Expression": {
            "Bennet": 0,
            "Biden": 38,
            "Bloomberg": 0,
            "Buttigieg": 42,
            "Delaney": 0,
            "Gabbard": 0,
            "Klobuchar": 0,
            "Patrick": 0,
            "Sanders": 23,
            "Steyer": 0,
            "Warren": 28,
            "Yang": 0,
            "Other": 0,
            "Uncommitted": 0
        },
        "Final Expression": {
            "Bennet": 0,
            "Biden": 47,
            "Bloomberg": 0,
            "Buttigieg": 51,
            "Delaney": 0,
            "Gabbard": 0,
            "Klobuchar": 0,
            "Patrick": 0,
            "Sanders": 23,
            "Steyer": 0,
            "Warren": 32,
            "Yang": 0,
            "Other": 0,
            "Uncommitted": 0
        },
        "Final Vote Increase": 22
    },
    {
        "County": "Polk",
        "Precinct": "ANKENY-14",
        "First Expression": {
            "Bennet": 0,
            "Biden": 36,
            "Bloomberg": 0,
            "Buttigieg": 92,
            "Delaney": 0,
            "Gabbard": 0,
            "Klobuchar": 19,
            "Patrick": 0,
            "Sanders": 75,
            "Steyer": 5,
            "Warren": 83,
            "Yang": 0,
            "Other": 0,
            "Uncommitted": 1
        },
        "Final Expression": {
            "Bennet": 0,
            "Biden": 0,
            "Bloomberg": 0,
            "Buttigieg": 149,
            "Delaney": 0,
            "Gabbard": 0,
            "Klobuchar": 0,
            "Patrick": 0,
            "Sanders": 83,
            "Steyer": 0,
            "Warren": 100,
            "Yang": 0,
            "Other": 0,
            "Uncommitted": 0
        },
        "Final Vote Increase": 21
    },
    {
        "County": "Dallas",
        "Precinct": "URBANDALE 13",
        "First Expression": {
            "Bennet": 0,
            "Biden": 58,
            "Bloomberg": 0,
            "Buttigieg": 99,
            "Delaney": 0,
            "Gabbard": 0,
            "Klobuchar": 51,
            "Patrick": 0,
            "Sanders": 54,
            "Steyer": 0,
            "Warren": 52,
            "Yang": 0,
            "Other": 0,
            "Uncommitted": 0
        },
        "Final Expression": {
            "Bennet": 0,
            "Biden": 58,
            "Bloomberg": 0,
            "Buttigieg": 110,
            "Delaney": 0,
            "Gabbard": 0,
            "Klobuchar": 57,
            "Patrick": 0,
            "Sanders": 58,
            "Steyer": 0,
            "Warren": 52,
            "Yang": 0,
            "Other": 0,
            "Uncommitted": 0
        },
        "Final Vote Increase": 21
    },
    {
        "County": "Benton",
        "Precinct": "Vinton 4",
        "First Expression": {
            "Bennet": 0,
            "Biden": 0,
            "Bloomberg": 0,
            "Buttigieg": 5,
            "Delaney": 0,
            "Gabbard": 0,
            "Klobuchar": 2,
            "Patrick": 0,
            "Sanders": 3,
            "Steyer": 0,
            "Warren": 0,
            "Yang": 0,
            "Other": 0,
            "Uncommitted": 0
        },
        "Final Expression": {
            "Bennet": 0,
            "Biden": 0,
            "Bloomberg": 0,
            "Buttigieg": 16,
            "Delaney": 0,
            "Gabbard": 0,
            "Klobuchar": 5,
            "Patrick": 0,
            "Sanders": 9,
            "Steyer": 0,
            "Warren": 0,
            "Yang": 0,
            "Other": 0,
            "Uncommitted": 0
        },
        "Final Vote Increase": 20
    },
    {
        "County": "Polk",
        "Precinct": "DES MOINES-07",
        "First Expression": {
            "Bennet": 0,
            "Biden": 0,
            "Bloomberg": 0,
            "Buttigieg": 47,
            "Delaney": 0,
            "Gabbard": 0,
            "Klobuchar": 0,
            "Patrick": 0,
            "Sanders": 91,
            "Steyer": 0,
            "Warren": 41,
            "Yang": 0,
            "Other": 0,
            "Uncommitted": 0
        },
        "Final Expression": {
            "Bennet": 0,
            "Biden": 0,
            "Bloomberg": 0,
            "Buttigieg": 53,
            "Delaney": 0,
            "Gabbard": 0,
            "Klobuchar": 0,
            "Patrick": 0,
            "Sanders": 96,
            "Steyer": 0,
            "Warren": 49,
            "Yang": 0,
            "Other": 0,
            "Uncommitted": 0
        },
        "Final Vote Increase": 19
    },
    {
        "County": "Linn",
        "Precinct": "Cedar Rapids 12",
        "First Expression": {
            "Bennet": 1,
            "Biden": 76,
            "Bloomberg": 5,
            "Buttigieg": 65,
            "Delaney": 0,
            "Gabbard": 0,
            "Klobuchar": 75,
            "Patrick": 0,
            "Sanders": 83,
            "Steyer": 4,
            "Warren": 60,
            "Yang": 4,
            "Other": 2,
            "Uncommitted": 5
        },
        "Final Expression": {
            "Bennet": 0,
            "Biden": 84,
            "Bloomberg": 0,
            "Buttigieg": 67,
            "Delaney": 0,
            "Gabbard": 0,
            "Klobuchar": 84,
            "Patrick": 0,
            "Sanders": 86,
            "Steyer": 0,
            "Warren": 67,
            "Yang": 0,
            "Other": 0,
            "Uncommitted": 7
        },
        "Final Vote Increase": 15
    },
    {
        "County": "Linn",
        "Precinct": "Cedar Rapids 28",
        "First Expression": {
            "Bennet": 0,
            "Biden": 40,
            "Bloomberg": 0,
            "Buttigieg": 29,
            "Delaney": 0,
            "Gabbard": 0,
            "Klobuchar": 0,
            "Patrick": 0,
            "Sanders": 49,
            "Steyer": 0,
            "Warren": 24,
            "Yang": 11,
            "Other": 0,
            "Uncommitted": 0
        },
        "Final Expression": {
            "Bennet": 0,
            "Biden": 41,
            "Bloomberg": 0,
            "Buttigieg": 43,
            "Delaney": 0,
            "Gabbard": 0,
            "Klobuchar": 0,
            "Patrick": 0,
            "Sanders": 53,
            "Steyer": 0,
            "Warren": 31,
            "Yang": 0,
            "Other": 0,
            "Uncommitted": 0
        },
        "Final Vote Increase": 15
    },
    {
        "County": "Scott",
        "Precinct": "(D11) City of Davenport",
        "First Expression": {
            "Bennet": 0,
            "Biden": 32,
            "Bloomberg": 0,
            "Buttigieg": 31,
            "Delaney": 0,
            "Gabbard": 0,
            "Klobuchar": 19,
            "Patrick": 0,
            "Sanders": 38,
            "Steyer": 3,
            "Warren": 15,
            "Yang": 9,
            "Other": 0,
            "Uncommitted": 0
        },
        "Final Expression": {
            "Bennet": 0,
            "Biden": 32,
            "Bloomberg": 0,
            "Buttigieg": 41,
            "Delaney": 0,
            "Gabbard": 0,
            "Klobuchar": 44,
            "Patrick": 0,
            "Sanders": 44,
            "Steyer": 0,
            "Warren": 0,
            "Yang": 0,
            "Other": 1,
            "Uncommitted": 0
        },
        "Final Vote Increase": 15
    },
    {
        "County": "Dubuque",
        "Precinct": "Dubuque_20",
        "First Expression": {
            "Bennet": 0,
            "Biden": 63,
            "Bloomberg": 0,
            "Buttigieg": 53,
            "Delaney": 0,
            "Gabbard": 0,
            "Klobuchar": 47,
            "Patrick": 0,
            "Sanders": 66,
            "Steyer": 0,
            "Warren": 43,
            "Yang": 0,
            "Other": 0,
            "Uncommitted": 0
        },
        "Final Expression": {
            "Bennet": 0,
            "Biden": 65,
            "Bloomberg": 0,
            "Buttigieg": 58,
            "Delaney": 0,
            "Gabbard": 0,
            "Klobuchar": 50,
            "Patrick": 0,
            "Sanders": 67,
            "Steyer": 0,
            "Warren": 46,
            "Yang": 0,
            "Other": 0,
            "Uncommitted": 0
        },
        "Final Vote Increase": 14
    },
    {
        "County": "Polk",
        "Precinct": "WDM-318",
        "First Expression": {
            "Bennet": 0,
            "Biden": 21,
            "Bloomberg": 0,
            "Buttigieg": 21,
            "Delaney": 0,
            "Gabbard": 0,
            "Klobuchar": 19,
            "Patrick": 0,
            "Sanders": 0,
            "Steyer": 0,
            "Warren": 0,
            "Yang": 0,
            "Other": 0,
            "Uncommitted": 0
        },
        "Final Expression": {
            "Bennet": 0,
            "Biden": 27,
            "Bloomberg": 0,
            "Buttigieg": 25,
            "Delaney": 0,
            "Gabbard": 0,
            "Klobuchar": 22,
            "Patrick": 0,
            "Sanders": 0,
            "Steyer": 0,
            "Warren": 0,
            "Yang": 0,
            "Other": 0,
            "Uncommitted": 0
        },
        "Final Vote Increase": 13
    },
    {
        "County": "Polk",
        "Precinct": "WDM-213",
        "First Expression": {
            "Bennet": 0,
            "Biden": 28,
            "Bloomberg": 2,
            "Buttigieg": 52,
            "Delaney": 0,
            "Gabbard": 0,
            "Klobuchar": 28,
            "Patrick": 0,
            "Sanders": 32,
            "Steyer": 0,
            "Warren": 34,
            "Yang": 0,
            "Other": 0,
            "Uncommitted": 0
        },
        "Final Expression": {
            "Bennet": 0,
            "Biden": 33,
            "Bloomberg": 0,
            "Buttigieg": 55,
            "Delaney": 0,
            "Gabbard": 0,
            "Klobuchar": 32,
            "Patrick": 0,
            "Sanders": 34,
            "Steyer": 0,
            "Warren": 34,
            "Yang": 0,
            "Other": 0,
            "Uncommitted": 0
        },
        "Final Vote Increase": 12
    },
    {
        "County": "Story",
        "Precinct": "Franklin Twp-Gilbert",
        "First Expression": {
            "Bennet": 0,
            "Biden": 49,
            "Bloomberg": 0,
            "Buttigieg": 82,
            "Delaney": 0,
            "Gabbard": 0,
            "Klobuchar": 64,
            "Patrick": 0,
            "Sanders": 56,
            "Steyer": 7,
            "Warren": 47,
            "Yang": 12,
            "Other": 1,
            "Uncommitted": 0
        },
        "Final Expression": {
            "Bennet": 0,
            "Biden": 49,
            "Bloomberg": 0,
            "Buttigieg": 87,
            "Delaney": 0,
            "Gabbard": 0,
            "Klobuchar": 68,
            "Patrick": 0,
            "Sanders": 61,
            "Steyer": 0,
            "Warren": 64,
            "Yang": 0,
            "Other": 0,
            "Uncommitted": 0
        },
        "Final Vote Increase": 11
    },
    {
        "County": "Polk",
        "Precinct": "WINDSOR HEIGHTS-02",
        "First Expression": {
            "Bennet": 0,
            "Biden": 39,
            "Bloomberg": 0,
            "Buttigieg": 59,
            "Delaney": 0,
            "Gabbard": 0,
            "Klobuchar": 48,
            "Patrick": 0,
            "Sanders": 40,
            "Steyer": 0,
            "Warren": 57,
            "Yang": 0,
            "Other": 0,
            "Uncommitted": 0
        },
        "Final Expression": {
            "Bennet": 0,
            "Biden": 40,
            "Bloomberg": 0,
            "Buttigieg": 61,
            "Delaney": 0,
            "Gabbard": 0,
            "Klobuchar": 48,
            "Patrick": 0,
            "Sanders": 43,
            "Steyer": 0,
            "Warren": 62,
            "Yang": 0,
            "Other": 0,
            "Uncommitted": 0
        },
        "Final Vote Increase": 11
    },
    {
        "County": "Woodbury",
        "Precinct": "Sioux City 06",
        "First Expression": {
            "Bennet": 0,
            "Biden": 23,
            "Bloomberg": 0,
            "Buttigieg": 23,
            "Delaney": 0,
            "Gabbard": 0,
            "Klobuchar": 25,
            "Patrick": 0,
            "Sanders": 32,
            "Steyer": 2,
            "Warren": 30,
            "Yang": 10,
            "Other": 0,
            "Uncommitted": 0
        },
        "Final Expression": {
            "Bennet": 0,
            "Biden": 26,
            "Bloomberg": 0,
            "Buttigieg": 27,
            "Delaney": 0,
            "Gabbard": 0,
            "Klobuchar": 25,
            "Patrick": 0,
            "Sanders": 43,
            "Steyer": 0,
            "Warren": 34,
            "Yang": 0,
            "Other": 0,
            "Uncommitted": 0
        },
        "Final Vote Increase": 10
    },
    {
        "County": "Polk",
        "Precinct": "DES MOINES-36",
        "First Expression": {
            "Bennet": 0,
            "Biden": 35,
            "Bloomberg": 0,
            "Buttigieg": 8,
            "Delaney": 0,
            "Gabbard": 0,
            "Klobuchar": 4,
            "Patrick": 0,
            "Sanders": 69,
            "Steyer": 1,
            "Warren": 4,
            "Yang": 7,
            "Other": 0,
            "Uncommitted": 0
        },
        "Final Expression": {
            "Bennet": 0,
            "Biden": 37,
            "Bloomberg": 0,
            "Buttigieg": 0,
            "Delaney": 0,
            "Gabbard": 0,
            "Klobuchar": 0,
            "Patrick": 0,
            "Sanders": 76,
            "Steyer": 1,
            "Warren": 23,
            "Yang": 1,
            "Other": 0,
            "Uncommitted": 0
        },
        "Final Vote Increase": 10
    },
    {
        "County": "Monona",
        "Precinct": "COOPER MAPLE MAPLETON",
        "First Expression": {
            "Bennet": 0,
            "Biden": 12,
            "Bloomberg": 0,
            "Buttigieg": 8,
            "Delaney": 0,
            "Gabbard": 0,
            "Klobuchar": 0,
            "Patrick": 0,
            "Sanders": 7,
            "Steyer": 0,
            "Warren": 7,
            "Yang": 0,
            "Other": 0,
            "Uncommitted": 0
        },
        "Final Expression": {
            "Bennet": 0,
            "Biden": 20,
            "Bloomberg": 0,
            "Buttigieg": 9,
            "Delaney": 0,
            "Gabbard": 0,
            "Klobuchar": 0,
            "Patrick": 0,
            "Sanders": 7,
            "Steyer": 0,
            "Warren": 7,
            "Yang": 0,
            "Other": 0,
            "Uncommitted": 0
        },
        "Final Vote Increase": 9
    },
    {
        "County": "Black Hawk",
        "Precinct": "WL 4-2",
        "First Expression": {
            "Bennet": 0,
            "Biden": 19,
            "Bloomberg": 0,
            "Buttigieg": 0,
            "Delaney": 0,
            "Gabbard": 0,
            "Klobuchar": 0,
            "Patrick": 0,
            "Sanders": 15,
            "Steyer": 0,
            "Warren": 11,
            "Yang": 0,
            "Other": 0,
            "Uncommitted": 0
        },
        "Final Expression": {
            "Bennet": 0,
            "Biden": 20,
            "Bloomberg": 0,
            "Buttigieg": 0,
            "Delaney": 0,
            "Gabbard": 0,
            "Klobuchar": 0,
            "Patrick": 0,
            "Sanders": 17,
            "Steyer": 0,
            "Warren": 17,
            "Yang": 0,
            "Other": 0,
            "Uncommitted": 0
        },
        "Final Vote Increase": 9
    },
    {
        "County": "Clayton",
        "Precinct": "CLAYTON-GARNAVILLO",
        "First Expression": {
            "Bennet": 0,
            "Biden": 12,
            "Bloomberg": 0,
            "Buttigieg": 5,
            "Delaney": 0,
            "Gabbard": 0,
            "Klobuchar": 7,
            "Patrick": 0,
            "Sanders": 7,
            "Steyer": 4,
            "Warren": 0,
            "Yang": 0,
            "Other": 0,
            "Uncommitted": 0
        },
        "Final Expression": {
            "Bennet": 0,
            "Biden": 12,
            "Bloomberg": 0,
            "Buttigieg": 8,
            "Delaney": 0,
            "Gabbard": 0,
            "Klobuchar": 8,
            "Patrick": 0,
            "Sanders": 7,
            "Steyer": 0,
            "Warren": 0,
            "Yang": 0,
            "Other": 8,
            "Uncommitted": 0
        },
        "Final Vote Increase": 8
    },
    {
        "County": "Fayette",
        "Precinct": "BETHEL-WINDSOR TWP",
        "First Expression": {
            "Bennet": 0,
            "Biden": 5,
            "Bloomberg": 0,
            "Buttigieg": 10,
            "Delaney": 0,
            "Gabbard": 0,
            "Klobuchar": 0,
            "Patrick": 0,
            "Sanders": 5,
            "Steyer": 0,
            "Warren": 8,
            "Yang": 0,
            "Other": 0,
            "Uncommitted": 0
        },
        "Final Expression": {
            "Bennet": 0,
            "Biden": 6,
            "Bloomberg": 0,
            "Buttigieg": 12,
            "Delaney": 0,
            "Gabbard": 0,
            "Klobuchar": 0,
            "Patrick": 0,
            "Sanders": 8,
            "Steyer": 0,
            "Warren": 9,
            "Yang": 0,
            "Other": 0,
            "Uncommitted": 0
        },
        "Final Vote Increase": 7
    },
    {
        "County": "Johnson",
        "Precinct": "SOLON",
        "First Expression": {
            "Bennet": 0,
            "Biden": 0,
            "Bloomberg": 0,
            "Buttigieg": 45,
            "Delaney": 0,
            "Gabbard": 1,
            "Klobuchar": 43,
            "Patrick": 0,
            "Sanders": 33,
            "Steyer": 3,
            "Warren": 49,
            "Yang": 1,
            "Other": 0,
            "Uncommitted": 0
        },
        "Final Expression": {
            "Bennet": 0,
            "Biden": 0,
            "Bloomberg": 0,
            "Buttigieg": 47,
            "Delaney": 0,
            "Gabbard": 0,
            "Klobuchar": 44,
            "Patrick": 0,
            "Sanders": 34,
            "Steyer": 0,
            "Warren": 56,
            "Yang": 0,
            "Other": 0,
            "Uncommitted": 0
        },
        "Final Vote Increase": 6
    },
    {
        "County": "Muscatine",
        "Precinct": "Fruitland Two/Lake-Fruitl",
        "First Expression": {
            "Bennet": 0,
            "Biden": 0,
            "Bloomberg": 0,
            "Buttigieg": 13,
            "Delaney": 0,
            "Gabbard": 0,
            "Klobuchar": 6,
            "Patrick": 0,
            "Sanders": 0,
            "Steyer": 0,
            "Warren": 5,
            "Yang": 0,
            "Other": 0,
            "Uncommitted": 0
        },
        "Final Expression": {
            "Bennet": 0,
            "Biden": 0,
            "Bloomberg": 0,
            "Buttigieg": 16,
            "Delaney": 0,
            "Gabbard": 0,
            "Klobuchar": 7,
            "Patrick": 0,
            "Sanders": 0,
            "Steyer": 0,
            "Warren": 7,
            "Yang": 0,
            "Other": 0,
            "Uncommitted": 0
        },
        "Final Vote Increase": 6
    },
    {
        "County": "Lucas",
        "Precinct": "Chariton Precinct 2",
        "First Expression": {
            "Bennet": 0,
            "Biden": 12,
            "Bloomberg": 0,
            "Buttigieg": 12,
            "Delaney": 0,
            "Gabbard": 0,
            "Klobuchar": 0,
            "Patrick": 0,
            "Sanders": 16,
            "Steyer": 0,
            "Warren": 10,
            "Yang": 0,
            "Other": 1,
            "Uncommitted": 0
        },
        "Final Expression": {
            "Bennet": 0,
            "Biden": 17,
            "Bloomberg": 0,
            "Buttigieg": 13,
            "Delaney": 0,
            "Gabbard": 0,
            "Klobuchar": 0,
            "Patrick": 0,
            "Sanders": 17,
            "Steyer": 0,
            "Warren": 10,
            "Yang": 0,
            "Other": 0,
            "Uncommitted": 0
        },
        "Final Vote Increase": 6
    },
    {
        "County": "Palo Alto",
        "Precinct": "EM Ward 4/FV/FR/VN/pt. EM",
        "First Expression": {
            "Bennet": 0,
            "Biden": 10,
            "Bloomberg": 1,
            "Buttigieg": 16,
            "Delaney": 0,
            "Gabbard": 0,
            "Klobuchar": 6,
            "Patrick": 0,
            "Sanders": 9,
            "Steyer": 1,
            "Warren": 6,
            "Yang": 1,
            "Other": 0,
            "Uncommitted": 0
        },
        "Final Expression": {
            "Bennet": 0,
            "Biden": 13,
            "Bloomberg": 0,
            "Buttigieg": 20,
            "Delaney": 0,
            "Gabbard": 0,
            "Klobuchar": 0,
            "Patrick": 0,
            "Sanders": 12,
            "Steyer": 0,
            "Warren": 10,
            "Yang": 0,
            "Other": 0,
            "Uncommitted": 0
        },
        "Final Vote Increase": 5
    },
    {
        "County": "Muscatine",
        "Precinct": "Muscatine 03rd",
        "First Expression": {
            "Bennet": 0,
            "Biden": 15,
            "Bloomberg": 0,
            "Buttigieg": 13,
            "Delaney": 0,
            "Gabbard": 1,
            "Klobuchar": 0,
            "Patrick": 0,
            "Sanders": 30,
            "Steyer": 1,
            "Warren": 9,
            "Yang": 6,
            "Other": 0,
            "Uncommitted": 0
        },
        "Final Expression": {
            "Bennet": 0,
            "Biden": 17,
            "Bloomberg": 0,
            "Buttigieg": 15,
            "Delaney": 0,
            "Gabbard": 0,
            "Klobuchar": 0,
            "Patrick": 0,
            "Sanders": 33,
            "Steyer": 0,
            "Warren": 15,
            "Yang": 0,
            "Other": 0,
            "Uncommitted": 0
        },
        "Final Vote Increase": 5
    },
    {
        "County": "Cherokee",
        "Precinct": "#6 Cherokee Ward 2",
        "First Expression": {
            "Bennet": 0,
            "Biden": 6,
            "Bloomberg": 0,
            "Buttigieg": 8,
            "Delaney": 0,
            "Gabbard": 0,
            "Klobuchar": 1,
            "Patrick": 0,
            "Sanders": 17,
            "Steyer": 0,
            "Warren": 0,
            "Yang": 0,
            "Other": 0,
            "Uncommitted": 0
        },
        "Final Expression": {
            "Bennet": 0,
            "Biden": 8,
            "Bloomberg": 0,
            "Buttigieg": 9,
            "Delaney": 0,
            "Gabbard": 0,
            "Klobuchar": 0,
            "Patrick": 0,
            "Sanders": 19,
            "Steyer": 0,
            "Warren": 0,
            "Yang": 0,
            "Other": 0,
            "Uncommitted": 0
        },
        "Final Vote Increase": 4
    },
    {
        "County": "Bremer",
        "Precinct": "WAVERLY WARD I/E WASHINGTON TWP",
        "First Expression": {
            "Bennet": 0,
            "Biden": 26,
            "Bloomberg": 0,
            "Buttigieg": 50,
            "Delaney": 0,
            "Gabbard": 0,
            "Klobuchar": 25,
            "Patrick": 0,
            "Sanders": 29,
            "Steyer": 2,
            "Warren": 31,
            "Yang": 0,
            "Other": 0,
            "Uncommitted": 1
        },
        "Final Expression": {
            "Bennet": 0,
            "Biden": 26,
            "Bloomberg": 0,
            "Buttigieg": 50,
            "Delaney": 0,
            "Gabbard": 0,
            "Klobuchar": 32,
            "Patrick": 0,
            "Sanders": 29,
            "Steyer": 0,
            "Warren": 31,
            "Yang": 0,
            "Other": 0,
            "Uncommitted": 0
        },
        "Final Vote Increase": 4
    },
    {
        "County": "Polk",
        "Precinct": "DES MOINES-02",
        "First Expression": {
            "Bennet": 0,
            "Biden": 20,
            "Bloomberg": 0,
            "Buttigieg": 7,
            "Delaney": 0,
            "Gabbard": 0,
            "Klobuchar": 8,
            "Patrick": 0,
            "Sanders": 30,
            "Steyer": 11,
            "Warren": 10,
            "Yang": 2,
            "Other": 0,
            "Uncommitted": 0
        },
        "Final Expression": {
            "Bennet": 0,
            "Biden": 20,
            "Bloomberg": 0,
            "Buttigieg": 0,
            "Delaney": 0,
            "Gabbard": 0,
            "Klobuchar": 18,
            "Patrick": 0,
            "Sanders": 38,
            "Steyer": 0,
            "Warren": 15,
            "Yang": 0,
            "Other": 0,
            "Uncommitted": 0
        },
        "Final Vote Increase": 3
    },
    {
        "County": "Dubuque",
        "Precinct": "Dubuque_14",
        "First Expression": {
            "Bennet": 0,
            "Biden": 3,
            "Bloomberg": 0,
            "Buttigieg": 16,
            "Delaney": 0,
            "Gabbard": 2,
            "Klobuchar": 6,
            "Patrick": 0,
            "Sanders": 39,
            "Steyer": 8,
            "Warren": 12,
            "Yang": 2,
            "Other": 0,
            "Uncommitted": 0
        },
        "Final Expression": {
            "Bennet": 0,
            "Biden": 0,
            "Bloomberg": 0,
            "Buttigieg": 30,
            "Delaney": 0,
            "Gabbard": 0,
            "Klobuchar": 0,
            "Patrick": 0,
            "Sanders": 42,
            "Steyer": 0,
            "Warren": 19,
            "Yang": 0,
            "Other": 0,
            "Uncommitted": 0
        },
        "Final Vote Increase": 3
    },
    {
        "County": "Dubuque",
        "Precinct": "Dubuque_07",
        "First Expression": {
            "Bennet": 0,
            "Biden": 56,
            "Bloomberg": 0,
            "Buttigieg": 51,
            "Delaney": 0,
            "Gabbard": 0,
            "Klobuchar": 25,
            "Patrick": 0,
            "Sanders": 45,
            "Steyer": 0,
            "Warren": 22,
            "Yang": 0,
            "Other": 0,
            "Uncommitted": 0
        },
        "Final Expression": {
            "Bennet": 0,
            "Biden": 57,
            "Bloomberg": 0,
            "Buttigieg": 63,
            "Delaney": 0,
            "Gabbard": 0,
            "Klobuchar": 0,
            "Patrick": 0,
            "Sanders": 46,
            "Steyer": 0,
            "Warren": 36,
            "Yang": 0,
            "Other": 0,
            "Uncommitted": 0
        },
        "Final Vote Increase": 3
    },
    {
        "County": "Johnson",
        "Precinct": "JW/MN/SW",
        "First Expression": {
            "Bennet": 0,
            "Biden": 30,
            "Bloomberg": 0,
            "Buttigieg": 40,
            "Delaney": 0,
            "Gabbard": 0,
            "Klobuchar": 29,
            "Patrick": 0,
            "Sanders": 35,
            "Steyer": 3,
            "Warren": 30,
            "Yang": 3,
            "Other": 0,
            "Uncommitted": 2
        },
        "Final Expression": {
            "Bennet": 0,
            "Biden": 31,
            "Bloomberg": 0,
            "Buttigieg": 40,
            "Delaney": 0,
            "Gabbard": 0,
            "Klobuchar": 31,
            "Patrick": 0,
            "Sanders": 37,
            "Steyer": 0,
            "Warren": 30,
            "Yang": 3,
            "Other": 0,
            "Uncommitted": 3
        },
        "Final Vote Increase": 3
    },
    {
        "County": "Polk",
        "Precinct": "DES MOINES-17",
        "First Expression": {
            "Bennet": 0,
            "Biden": 20,
            "Bloomberg": 0,
            "Buttigieg": 12,
            "Delaney": 0,
            "Gabbard": 0,
            "Klobuchar": 10,
            "Patrick": 0,
            "Sanders": 35,
            "Steyer": 3,
            "Warren": 11,
            "Yang": 0,
            "Other": 0,
            "Uncommitted": 0
        },
        "Final Expression": {
            "Bennet": 0,
            "Biden": 27,
            "Bloomberg": 0,
            "Buttigieg": 0,
            "Delaney": 0,
            "Gabbard": 0,
            "Klobuchar": 0,
            "Patrick": 0,
            "Sanders": 40,
            "Steyer": 0,
            "Warren": 27,
            "Yang": 0,
            "Other": 0,
            "Uncommitted": 0
        },
        "Final Vote Increase": 3
    },
    {
        "County": "Wright",
        "Precinct": "Eagle Grove #4",
        "First Expression": {
            "Bennet": 0,
            "Biden": 4,
            "Bloomberg": 0,
            "Buttigieg": 4,
            "Delaney": 0,
            "Gabbard": 0,
            "Klobuchar": 6,
            "Patrick": 0,
            "Sanders": 5,
            "Steyer": 0,
            "Warren": 3,
            "Yang": 0,
            "Other": 0,
            "Uncommitted": 1
        },
        "Final Expression": {
            "Bennet": 0,
            "Biden": 4,
            "Bloomberg": 0,
            "Buttigieg": 8,
            "Delaney": 0,
            "Gabbard": 0,
            "Klobuchar": 7,
            "Patrick": 0,
            "Sanders": 6,
            "Steyer": 0,
            "Warren": 0,
            "Yang": 0,
            "Other": 0,
            "Uncommitted": 1
        },
        "Final Vote Increase": 3
    },
    {
        "County": "Polk",
        "Precinct": "DES MOINES-05",
        "First Expression": {
            "Bennet": 0,
            "Biden": 0,
            "Bloomberg": 0,
            "Buttigieg": 13,
            "Delaney": 0,
            "Gabbard": 0,
            "Klobuchar": 8,
            "Patrick": 0,
            "Sanders": 32,
            "Steyer": 2,
            "Warren": 11,
            "Yang": 6,
            "Other": 0,
            "Uncommitted": 0
        },
        "Final Expression": {
            "Bennet": 0,
            "Biden": 0,
            "Bloomberg": 0,
            "Buttigieg": 15,
            "Delaney": 0,
            "Gabbard": 0,
            "Klobuchar": 12,
            "Patrick": 0,
            "Sanders": 35,
            "Steyer": 0,
            "Warren": 12,
            "Yang": 0,
            "Other": 0,
            "Uncommitted": 0
        },
        "Final Vote Increase": 2
    },
    {
        "County": "Polk",
        "Precinct": "DES MOINES-69",
        "First Expression": {
            "Bennet": 0,
            "Biden": 28,
            "Bloomberg": 0,
            "Buttigieg": 33,
            "Delaney": 0,
            "Gabbard": 0,
            "Klobuchar": 12,
            "Patrick": 0,
            "Sanders": 52,
            "Steyer": 0,
            "Warren": 22,
            "Yang": 6,
            "Other": 0,
            "Uncommitted": 2
        },
        "Final Expression": {
            "Bennet": 0,
            "Biden": 33,
            "Bloomberg": 0,
            "Buttigieg": 50,
            "Delaney": 0,
            "Gabbard": 0,
            "Klobuchar": 0,
            "Patrick": 0,
            "Sanders": 74,
            "Steyer": 0,
            "Warren": 0,
            "Yang": 0,
            "Other": 0,
            "Uncommitted": 0
        },
        "Final Vote Increase": 2
    },
    {
        "County": "Pottawattamie",
        "Precinct": "Council Bluff 08",
        "First Expression": {
            "Bennet": 0,
            "Biden": 14,
            "Bloomberg": 0,
            "Buttigieg": 27,
            "Delaney": 0,
            "Gabbard": 1,
            "Klobuchar": 30,
            "Patrick": 0,
            "Sanders": 36,
            "Steyer": 0,
            "Warren": 38,
            "Yang": 7,
            "Other": 0,
            "Uncommitted": 0
        },
        "Final Expression": {
            "Bennet": 0,
            "Biden": 0,
            "Bloomberg": 0,
            "Buttigieg": 37,
            "Delaney": 0,
            "Gabbard": 0,
            "Klobuchar": 34,
            "Patrick": 0,
            "Sanders": 38,
            "Steyer": 0,
            "Warren": 38,
            "Yang": 0,
            "Other": 0,
            "Uncommitted": 8
        },
        "Final Vote Increase": 2
    },
    {
        "County": "Adair",
        "Precinct": "4SE ORIENT",
        "First Expression": {
            "Bennet": 0,
            "Biden": 7,
            "Bloomberg": 0,
            "Buttigieg": 6,
            "Delaney": 0,
            "Gabbard": 0,
            "Klobuchar": 6,
            "Patrick": 0,
            "Sanders": 6,
            "Steyer": 0,
            "Warren": 9,
            "Yang": 0,
            "Other": 0,
            "Uncommitted": 0
        },
        "Final Expression": {
            "Bennet": 0,
            "Biden": 7,
            "Bloomberg": 0,
            "Buttigieg": 6,
            "Delaney": 0,
            "Gabbard": 0,
            "Klobuchar": 8,
            "Patrick": 0,
            "Sanders": 6,
            "Steyer": 0,
            "Warren": 9,
            "Yang": 0,
            "Other": 0,
            "Uncommitted": 0
        },
        "Final Vote Increase": 2
    },
    {
        "County": "Black Hawk",
        "Precinct": "CF W3 P1",
        "First Expression": {
            "Bennet": 0,
            "Biden": 32,
            "Bloomberg": 0,
            "Buttigieg": 54,
            "Delaney": 0,
            "Gabbard": 0,
            "Klobuchar": 51,
            "Patrick": 0,
            "Sanders": 37,
            "Steyer": 0,
            "Warren": 23,
            "Yang": 9,
            "Other": 0,
            "Uncommitted": 0
        },
        "Final Expression": {
            "Bennet": 0,
            "Biden": 33,
            "Bloomberg": 0,
            "Buttigieg": 63,
            "Delaney": 0,
            "Gabbard": 0,
            "Klobuchar": 61,
            "Patrick": 0,
            "Sanders": 51,
            "Steyer": 0,
            "Warren": 0,
            "Yang": 0,
            "Other": 0,
            "Uncommitted": 0
        },
        "Final Vote Increase": 2
    },
    {
        "County": "Linn",
        "Precinct": "Cedar Rapids 24",
        "First Expression": {
            "Bennet": 3,
            "Biden": 77,
            "Bloomberg": 0,
            "Buttigieg": 72,
            "Delaney": 0,
            "Gabbard": 0,
            "Klobuchar": 93,
            "Patrick": 0,
            "Sanders": 67,
            "Steyer": 0,
            "Warren": 115,
            "Yang": 9,
            "Other": 0,
            "Uncommitted": 0
        },
        "Final Expression": {
            "Bennet": 0,
            "Biden": 82,
            "Bloomberg": 0,
            "Buttigieg": 72,
            "Delaney": 0,
            "Gabbard": 0,
            "Klobuchar": 99,
            "Patrick": 0,
            "Sanders": 69,
            "Steyer": 0,
            "Warren": 116,
            "Yang": 0,
            "Other": 0,
            "Uncommitted": 0
        },
        "Final Vote Increase": 2
    },
    {
        "County": "Jasper",
        "Precinct": "Newton/Sherman",
        "First Expression": {
            "Bennet": 0,
            "Biden": 19,
            "Bloomberg": 0,
            "Buttigieg": 37,
            "Delaney": 0,
            "Gabbard": 0,
            "Klobuchar": 10,
            "Patrick": 0,
            "Sanders": 19,
            "Steyer": 4,
            "Warren": 16,
            "Yang": 6,
            "Other": 0,
            "Uncommitted": 0
        },
        "Final Expression": {
            "Bennet": 0,
            "Biden": 23,
            "Bloomberg": 0,
            "Buttigieg": 45,
            "Delaney": 0,
            "Gabbard": 0,
            "Klobuchar": 0,
            "Patrick": 0,
            "Sanders": 25,
            "Steyer": 0,
            "Warren": 20,
            "Yang": 0,
            "Other": 0,
            "Uncommitted": 0
        },
        "Final Vote Increase": 2
    },
    {
        "County": "Henry",
        "Precinct": "Southeast Precinct",
        "First Expression": {
            "Bennet": 0,
            "Biden": 17,
            "Bloomberg": 0,
            "Buttigieg": 28,
            "Delaney": 0,
            "Gabbard": 1,
            "Klobuchar": 4,
            "Patrick": 0,
            "Sanders": 37,
            "Steyer": 4,
            "Warren": 4,
            "Yang": 14,
            "Other": 0,
            "Uncommitted": 0
        },
        "Final Expression": {
            "Bennet": 0,
            "Biden": 21,
            "Bloomberg": 0,
            "Buttigieg": 31,
            "Delaney": 0,
            "Gabbard": 0,
            "Klobuchar": 0,
            "Patrick": 0,
            "Sanders": 41,
            "Steyer": 0,
            "Warren": 0,
            "Yang": 18,
            "Other": 0,
            "Uncommitted": 0
        },
        "Final Vote Increase": 2
    },
    {
        "County": "Boone",
        "Precinct": "Boone 4th Ward",
        "First Expression": {
            "Bennet": 0,
            "Biden": 22,
            "Bloomberg": 0,
            "Buttigieg": 29,
            "Delaney": 0,
            "Gabbard": 0,
            "Klobuchar": 11,
            "Patrick": 0,
            "Sanders": 41,
            "Steyer": 2,
            "Warren": 25,
            "Yang": 8,
            "Other": 0,
            "Uncommitted": 1
        },
        "Final Expression": {
            "Bennet": 0,
            "Biden": 27,
            "Bloomberg": 0,
            "Buttigieg": 36,
            "Delaney": 0,
            "Gabbard": 0,
            "Klobuchar": 0,
            "Patrick": 0,
            "Sanders": 47,
            "Steyer": 0,
            "Warren": 31,
            "Yang": 0,
            "Other": 0,
            "Uncommitted": 0
        },
        "Final Vote Increase": 2
    },
    {
        "County": "Black Hawk",
        "Precinct": "WL 1-3",
        "First Expression": {
            "Bennet": 0,
            "Biden": 10,
            "Bloomberg": 0,
            "Buttigieg": 8,
            "Delaney": 0,
            "Gabbard": 1,
            "Klobuchar": 7,
            "Patrick": 0,
            "Sanders": 43,
            "Steyer": 0,
            "Warren": 16,
            "Yang": 0,
            "Other": 0,
            "Uncommitted": 0
        },
        "Final Expression": {
            "Bennet": 0,
            "Biden": 17,
            "Bloomberg": 0,
            "Buttigieg": 0,
            "Delaney": 0,
            "Gabbard": 0,
            "Klobuchar": 0,
            "Patrick": 0,
            "Sanders": 43,
            "Steyer": 0,
            "Warren": 27,
            "Yang": 0,
            "Other": 0,
            "Uncommitted": 0
        },
        "Final Vote Increase": 2
    },
    {
        "County": "Mahaska",
        "Precinct": "CEDAR - HARRISON - WHITE OAK",
        "First Expression": {
            "Bennet": 0,
            "Biden": 10,
            "Bloomberg": 0,
            "Buttigieg": 0,
            "Delaney": 0,
            "Gabbard": 0,
            "Klobuchar": 9,
            "Patrick": 0,
            "Sanders": 15,
            "Steyer": 0,
            "Warren": 5,
            "Yang": 8,
            "Other": 0,
            "Uncommitted": 0
        },
        "Final Expression": {
            "Bennet": 0,
            "Biden": 10,
            "Bloomberg": 0,
            "Buttigieg": 0,
            "Delaney": 0,
            "Gabbard": 0,
            "Klobuchar": 14,
            "Patrick": 0,
            "Sanders": 16,
            "Steyer": 0,
            "Warren": 0,
            "Yang": 8,
            "Other": 0,
            "Uncommitted": 0
        },
        "Final Vote Increase": 1
    },
    {
        "County": "Sioux",
        "Precinct": "HW/BC/LG/WA/EG S",
        "First Expression": {
            "Bennet": 0,
            "Biden": 14,
            "Bloomberg": 0,
            "Buttigieg": 24,
            "Delaney": 0,
            "Gabbard": 0,
            "Klobuchar": 1,
            "Patrick": 0,
            "Sanders": 44,
            "Steyer": 0,
            "Warren": 6,
            "Yang": 2,
            "Other": 0,
            "Uncommitted": 0
        },
        "Final Expression": {
            "Bennet": 0,
            "Biden": 18,
            "Bloomberg": 0,
            "Buttigieg": 28,
            "Delaney": 0,
            "Gabbard": 0,
            "Klobuchar": 0,
            "Patrick": 0,
            "Sanders": 45,
            "Steyer": 0,
            "Warren": 0,
            "Yang": 0,
            "Other": 0,
            "Uncommitted": 1
        },
        "Final Vote Increase": 1
    },
    {
        "County": "Pottawattamie",
        "Precinct": "Crescent",
        "First Expression": {
            "Bennet": 0,
            "Biden": 34,
            "Bloomberg": 0,
            "Buttigieg": 25,
            "Delaney": 0,
            "Gabbard": 0,
            "Klobuchar": 21,
            "Patrick": 0,
            "Sanders": 15,
            "Steyer": 7,
            "Warren": 14,
            "Yang": 6,
            "Other": 0,
            "Uncommitted": 0
        },
        "Final Expression": {
            "Bennet": 0,
            "Biden": 34,
            "Bloomberg": 0,
            "Buttigieg": 32,
            "Delaney": 0,
            "Gabbard": 0,
            "Klobuchar": 25,
            "Patrick": 0,
            "Sanders": 23,
            "Steyer": 0,
            "Warren": 7,
            "Yang": 2,
            "Other": 0,
            "Uncommitted": 0
        },
        "Final Vote Increase": 1
    },
    {
        "County": "Ringgold",
        "Precinct": "Athens",
        "First Expression": {
            "Bennet": 0,
            "Biden": 2,
            "Bloomberg": 0,
            "Buttigieg": 3,
            "Delaney": 0,
            "Gabbard": 0,
            "Klobuchar": 3,
            "Patrick": 0,
            "Sanders": 0,
            "Steyer": 0,
            "Warren": 0,
            "Yang": 0,
            "Other": 0,
            "Uncommitted": 0
        },
        "Final Expression": {
            "Bennet": 0,
            "Biden": 3,
            "Bloomberg": 0,
            "Buttigieg": 3,
            "Delaney": 0,
            "Gabbard": 0,
            "Klobuchar": 3,
            "Patrick": 0,
            "Sanders": 0,
            "Steyer": 0,
            "Warren": 0,
            "Yang": 0,
            "Other": 0,
            "Uncommitted": 0
        },
        "Final Vote Increase": 1
    },
    {
        "County": "Ringgold",
        "Precinct": "Clinton",
        "First Expression": {
            "Bennet": 0,
            "Biden": 4,
            "Bloomberg": 0,
            "Buttigieg": 0,
            "Delaney": 0,
            "Gabbard": 0,
            "Klobuchar": 8,
            "Patrick": 0,
            "Sanders": 0,
            "Steyer": 0,
            "Warren": 0,
            "Yang": 0,
            "Other": 0,
            "Uncommitted": 0
        },
        "Final Expression": {
            "Bennet": 0,
            "Biden": 4,
            "Bloomberg": 0,
            "Buttigieg": 0,
            "Delaney": 0,
            "Gabbard": 0,
            "Klobuchar": 9,
            "Patrick": 0,
            "Sanders": 0,
            "Steyer": 0,
            "Warren": 0,
            "Yang": 0,
            "Other": 0,
            "Uncommitted": 0
        },
        "Final Vote Increase": 1
    },
    {
        "County": "Black Hawk",
        "Precinct": "WL 3-4",
        "First Expression": {
            "Bennet": 0,
            "Biden": 7,
            "Bloomberg": 0,
            "Buttigieg": 5,
            "Delaney": 0,
            "Gabbard": 0,
            "Klobuchar": 0,
            "Patrick": 0,
            "Sanders": 19,
            "Steyer": 3,
            "Warren": 7,
            "Yang": 1,
            "Other": 0,
            "Uncommitted": 0
        },
        "Final Expression": {
            "Bennet": 0,
            "Biden": 14,
            "Bloomberg": 0,
            "Buttigieg": 0,
            "Delaney": 0,
            "Gabbard": 0,
            "Klobuchar": 0,
            "Patrick": 0,
            "Sanders": 21,
            "Steyer": 0,
            "Warren": 8,
            "Yang": 0,
            "Other": 0,
            "Uncommitted": 0
        },
        "Final Vote Increase": 1
    },
    {
        "County": "Scott",
        "Precinct": "(D24) City of Davenport",
        "First Expression": {
            "Bennet": 0,
            "Biden": 23,
            "Bloomberg": 0,
            "Buttigieg": 24,
            "Delaney": 0,
            "Gabbard": 0,
            "Klobuchar": 14,
            "Patrick": 0,
            "Sanders": 23,
            "Steyer": 14,
            "Warren": 15,
            "Yang": 11,
            "Other": 0,
            "Uncommitted": 1
        },
        "Final Expression": {
            "Bennet": 0,
            "Biden": 28,
            "Bloomberg": 0,
            "Buttigieg": 33,
            "Delaney": 0,
            "Gabbard": 0,
            "Klobuchar": 19,
            "Patrick": 0,
            "Sanders": 31,
            "Steyer": 0,
            "Warren": 15,
            "Yang": 0,
            "Other": 0,
            "Uncommitted": 0
        },
        "Final Vote Increase": 1
    },
    {
        "County": "Wapello",
        "Precinct": "Washington/Eldon",
        "First Expression": {
            "Bennet": 0,
            "Biden": 7,
            "Bloomberg": 0,
            "Buttigieg": 15,
            "Delaney": 0,
            "Gabbard": 0,
            "Klobuchar": 0,
            "Patrick": 0,
            "Sanders": 3,
            "Steyer": 0,
            "Warren": 0,
            "Yang": 0,
            "Other": 0,
            "Uncommitted": 0
        },
        "Final Expression": {
            "Bennet": 0,
            "Biden": 7,
            "Bloomberg": 0,
            "Buttigieg": 15,
            "Delaney": 0,
            "Gabbard": 0,
            "Klobuchar": 0,
            "Patrick": 0,
            "Sanders": 4,
            "Steyer": 0,
            "Warren": 0,
            "Yang": 0,
            "Other": 0,
            "Uncommitted": 0
        },
        "Final Vote Increase": 1
    },
    {
        "County": "Story",
        "Precinct": "Ames 4-1",
        "First Expression": {
            "Bennet": 1,
            "Biden": 1,
            "Bloomberg": 0,
            "Buttigieg": 103,
            "Delaney": 0,
            "Gabbard": 1,
            "Klobuchar": 3,
            "Patrick": 0,
            "Sanders": 151,
            "Steyer": 4,
            "Warren": 92,
            "Yang": 70,
            "Other": 0,
            "Uncommitted": 0
        },
        "Final Expression": {
            "Bennet": 0,
            "Biden": 0,
            "Bloomberg": 0,
            "Buttigieg": 106,
            "Delaney": 0,
            "Gabbard": 0,
            "Klobuchar": 0,
            "Patrick": 0,
            "Sanders": 152,
            "Steyer": 0,
            "Warren": 96,
            "Yang": 73,
            "Other": 0,
            "Uncommitted": 0
        },
        "Final Vote Increase": 1
    },
    {
        "County": "Black Hawk",
        "Precinct": "CF W4 P3",
        "First Expression": {
            "Bennet": 0,
            "Biden": 4,
            "Bloomberg": 0,
            "Buttigieg": 70,
            "Delaney": 0,
            "Gabbard": 0,
            "Klobuchar": 8,
            "Patrick": 0,
            "Sanders": 115,
            "Steyer": 1,
            "Warren": 76,
            "Yang": 8,
            "Other": 0,
            "Uncommitted": 0
        },
        "Final Expression": {
            "Bennet": 0,
            "Biden": 0,
            "Bloomberg": 0,
            "Buttigieg": 78,
            "Delaney": 0,
            "Gabbard": 0,
            "Klobuchar": 0,
            "Patrick": 0,
            "Sanders": 122,
            "Steyer": 0,
            "Warren": 83,
            "Yang": 0,
            "Other": 0,
            "Uncommitted": 0
        },
        "Final Vote Increase": 1
    },
    {
        "County": "Black Hawk",
        "Precinct": "CF W3 P2",
        "First Expression": {
            "Bennet": 0,
            "Biden": 45,
            "Bloomberg": 0,
            "Buttigieg": 63,
            "Delaney": 0,
            "Gabbard": 0,
            "Klobuchar": 54,
            "Patrick": 0,
            "Sanders": 60,
            "Steyer": 3,
            "Warren": 44,
            "Yang": 7,
            "Other": 0,
            "Uncommitted": 0
        },
        "Final Expression": {
            "Bennet": 0,
            "Biden": 46,
            "Bloomberg": 0,
            "Buttigieg": 66,
            "Delaney": 0,
            "Gabbard": 0,
            "Klobuchar": 58,
            "Patrick": 0,
            "Sanders": 61,
            "Steyer": 0,
            "Warren": 46,
            "Yang": 0,
            "Other": 0,
            "Uncommitted": 0
        },
        "Final Vote Increase": 1
    },
    {
        "County": "Webster",
        "Precinct": "Fort Dodge 09",
        "First Expression": {
            "Bennet": 0,
            "Biden": 7,
            "Bloomberg": 0,
            "Buttigieg": 13,
            "Delaney": 0,
            "Gabbard": 0,
            "Klobuchar": 2,
            "Patrick": 0,
            "Sanders": 11,
            "Steyer": 0,
            "Warren": 7,
            "Yang": 4,
            "Other": 0,
            "Uncommitted": 0
        },
        "Final Expression": {
            "Bennet": 0,
            "Biden": 9,
            "Bloomberg": 0,
            "Buttigieg": 16,
            "Delaney": 0,
            "Gabbard": 0,
            "Klobuchar": 0,
            "Patrick": 0,
            "Sanders": 13,
            "Steyer": 0,
            "Warren": 7,
            "Yang": 0,
            "Other": 0,
            "Uncommitted": 0
        },
        "Final Vote Increase": 1
    },
    {
        "County": "Woodbury",
        "Precinct": "44 Cushing/Rock",
        "First Expression": {
            "Bennet": 0,
            "Biden": 5,
            "Bloomberg": 0,
            "Buttigieg": 2,
            "Delaney": 0,
            "Gabbard": 0,
            "Klobuchar": 0,
            "Patrick": 0,
            "Sanders": 1,
            "Steyer": 0,
            "Warren": 0,
            "Yang": 0,
            "Other": 0,
            "Uncommitted": 0
        },
        "Final Expression": {
            "Bennet": 0,
            "Biden": 5,
            "Bloomberg": 0,
            "Buttigieg": 2,
            "Delaney": 0,
            "Gabbard": 0,
            "Klobuchar": 0,
            "Patrick": 0,
            "Sanders": 1,
            "Steyer": 0,
            "Warren": 1,
            "Yang": 0,
            "Other": 0,
            "Uncommitted": 0
        },
        "Final Vote Increase": 1
    },
    {
        "County": "Black Hawk",
        "Precinct": "Washington Janesville",
        "First Expression": {
            "Bennet": 0,
            "Biden": 6,
            "Bloomberg": 0,
            "Buttigieg": 6,
            "Delaney": 0,
            "Gabbard": 0,
            "Klobuchar": 0,
            "Patrick": 0,
            "Sanders": 6,
            "Steyer": 3,
            "Warren": 4,
            "Yang": 0,
            "Other": 0,
            "Uncommitted": 0
        },
        "Final Expression": {
            "Bennet": 0,
            "Biden": 0,
            "Bloomberg": 0,
            "Buttigieg": 14,
            "Delaney": 0,
            "Gabbard": 0,
            "Klobuchar": 0,
            "Patrick": 0,
            "Sanders": 12,
            "Steyer": 0,
            "Warren": 0,
            "Yang": 0,
            "Other": 0,
            "Uncommitted": 0
        },
        "Final Vote Increase": 1
    },
    {
        "County": "CD2 Satellite",
        "Precinct": "Iowa City, IA - Walden Place Retirement Community",
        "First Expression": {
            "Bennet": 0,
            "Biden": 7,
            "Bloomberg": 0,
            "Buttigieg": 0,
            "Delaney": 0,
            "Gabbard": 0,
            "Klobuchar": 4,
            "Patrick": 0,
            "Sanders": 0,
            "Steyer": 0,
            "Warren": 4,
            "Yang": 0,
            "Other": 0,
            "Uncommitted": 6
        },
        "Final Expression": {
            "Bennet": 0,
            "Biden": 7,
            "Bloomberg": 0,
            "Buttigieg": 0,
            "Delaney": 0,
            "Gabbard": 0,
            "Klobuchar": 4,
            "Patrick": 0,
            "Sanders": 0,
            "Steyer": 0,
            "Warren": 5,
            "Yang": 0,
            "Other": 0,
            "Uncommitted": 6
        },
        "Final Vote Increase": 1
    },
    {
        "County": "Buchanan",
        "Precinct": "Independence 5th Ward",
        "First Expression": {
            "Bennet": 0,
            "Biden": 17,
            "Bloomberg": 0,
            "Buttigieg": 14,
            "Delaney": 0,
            "Gabbard": 0,
            "Klobuchar": 0,
            "Patrick": 0,
            "Sanders": 10,
            "Steyer": 5,
            "Warren": 4,
            "Yang": 0,
            "Other": 0,
            "Uncommitted": 0
        },
        "Final Expression": {
            "Bennet": 0,
            "Biden": 17,
            "Bloomberg": 0,
            "Buttigieg": 14,
            "Delaney": 0,
            "Gabbard": 0,
            "Klobuchar": 0,
            "Patrick": 0,
            "Sanders": 11,
            "Steyer": 9,
            "Warren": 0,
            "Yang": 0,
            "Other": 0,
            "Uncommitted": 0
        },
        "Final Vote Increase": 1
    },
    {
        "County": "Linn",
        "Precinct": "Hiawatha 1",
        "First Expression": {
            "Bennet": 0,
            "Biden": 37,
            "Bloomberg": 0,
            "Buttigieg": 29,
            "Delaney": 0,
            "Gabbard": 0,
            "Klobuchar": 42,
            "Patrick": 0,
            "Sanders": 46,
            "Steyer": 8,
            "Warren": 25,
            "Yang": 2,
            "Other": 0,
            "Uncommitted": 0
        },
        "Final Expression": {
            "Bennet": 0,
            "Biden": 40,
            "Bloomberg": 0,
            "Buttigieg": 35,
            "Delaney": 0,
            "Gabbard": 0,
            "Klobuchar": 55,
            "Patrick": 0,
            "Sanders": 55,
            "Steyer": 0,
            "Warren": 0,
            "Yang": 0,
            "Other": 5,
            "Uncommitted": 0
        },
        "Final Vote Increase": 1
    },
    {
        "County": "Cass",
        "Precinct": "Atlantic 5",
        "First Expression": {
            "Bennet": 0,
            "Biden": 11,
            "Bloomberg": 0,
            "Buttigieg": 10,
            "Delaney": 0,
            "Gabbard": 0,
            "Klobuchar": 9,
            "Patrick": 0,
            "Sanders": 4,
            "Steyer": 2,
            "Warren": 12,
            "Yang": 0,
            "Other": 0,
            "Uncommitted": 0
        },
        "Final Expression": {
            "Bennet": 0,
            "Biden": 13,
            "Bloomberg": 0,
            "Buttigieg": 11,
            "Delaney": 0,
            "Gabbard": 0,
            "Klobuchar": 10,
            "Patrick": 0,
            "Sanders": 0,
            "Steyer": 0,
            "Warren": 15,
            "Yang": 0,
            "Other": 0,
            "Uncommitted": 0
        },
        "Final Vote Increase": 1
    },
    {
        "County": "Polk",
        "Precinct": "WDM-113",
        "First Expression": {
            "Bennet": 0,
            "Biden": 15,
            "Bloomberg": 1,
            "Buttigieg": 56,
            "Delaney": 0,
            "Gabbard": 1,
            "Klobuchar": 10,
            "Patrick": 0,
            "Sanders": 89,
            "Steyer": 1,
            "Warren": 38,
            "Yang": 9,
            "Other": 0,
            "Uncommitted": 0
        },
        "Final Expression": {
            "Bennet": 0,
            "Biden": 0,
            "Bloomberg": 0,
            "Buttigieg": 59,
            "Delaney": 0,
            "Gabbard": 0,
            "Klobuchar": 0,
            "Patrick": 0,
            "Sanders": 94,
            "Steyer": 0,
            "Warren": 51,
            "Yang": 0,
            "Other": 0,
            "Uncommitted": 17
        },
        "Final Vote Increase": 1
    },
    {
        "County": "Cedar",
        "Precinct": "TIPTON 1",
        "First Expression": {
            "Bennet": 0,
            "Biden": 6,
            "Bloomberg": 0,
            "Buttigieg": 7,
            "Delaney": 0,
            "Gabbard": 0,
            "Klobuchar": 6,
            "Patrick": 0,
            "Sanders": 9,
            "Steyer": 2,
            "Warren": 4,
            "Yang": 0,
            "Other": 0,
            "Uncommitted": 0
        },
        "Final Expression": {
            "Bennet": 0,
            "Biden": 6,
            "Bloomberg": 0,
            "Buttigieg": 9,
            "Delaney": 0,
            "Gabbard": 0,
            "Klobuchar": 7,
            "Patrick": 0,
            "Sanders": 13,
            "Steyer": 0,
            "Warren": 0,
            "Yang": 0,
            "Other": 0,
            "Uncommitted": 0
        },
        "Final Vote Increase": 1
    },
    {
        "County": "Polk",
        "Precinct": "JOHNSTON-05",
        "First Expression": {
            "Bennet": 0,
            "Biden": 75,
            "Bloomberg": 0,
            "Buttigieg": 148,
            "Delaney": 0,
            "Gabbard": 0,
            "Klobuchar": 70,
            "Patrick": 0,
            "Sanders": 96,
            "Steyer": 13,
            "Warren": 79,
            "Yang": 3,
            "Other": 0,
            "Uncommitted": 0
        },
        "Final Expression": {
            "Bennet": 0,
            "Biden": 79,
            "Bloomberg": 0,
            "Buttigieg": 152,
            "Delaney": 0,
            "Gabbard": 0,
            "Klobuchar": 75,
            "Patrick": 0,
            "Sanders": 99,
            "Steyer": 0,
            "Warren": 80,
            "Yang": 0,
            "Other": 0,
            "Uncommitted": 0
        },
        "Final Vote Increase": 1
    },
    {
        "County": "Cerro Gordo",
        "Precinct": "Clear Lake - Ward 1",
        "First Expression": {
            "Bennet": 0,
            "Biden": 15,
            "Bloomberg": 0,
            "Buttigieg": 22,
            "Delaney": 0,
            "Gabbard": 0,
            "Klobuchar": 23,
            "Patrick": 0,
            "Sanders": 13,
            "Steyer": 7,
            "Warren": 12,
            "Yang": 6,
            "Other": 0,
            "Uncommitted": 0
        },
        "Final Expression": {
            "Bennet": 0,
            "Biden": 15,
            "Bloomberg": 0,
            "Buttigieg": 27,
            "Delaney": 0,
            "Gabbard": 0,
            "Klobuchar": 27,
            "Patrick": 0,
            "Sanders": 15,
            "Steyer": 0,
            "Warren": 15,
            "Yang": 0,
            "Other": 0,
            "Uncommitted": 0
        },
        "Final Vote Increase": 1
    },
    {
        "County": "Cerro Gordo",
        "Precinct": "Mason City W-2 P-1",
        "First Expression": {
            "Bennet": 0,
            "Biden": 14,
            "Bloomberg": 0,
            "Buttigieg": 14,
            "Delaney": 0,
            "Gabbard": 0,
            "Klobuchar": 7,
            "Patrick": 0,
            "Sanders": 28,
            "Steyer": 0,
            "Warren": 8,
            "Yang": 7,
            "Other": 0,
            "Uncommitted": 0
        },
        "Final Expression": {
            "Bennet": 0,
            "Biden": 23,
            "Bloomberg": 0,
            "Buttigieg": 23,
            "Delaney": 0,
            "Gabbard": 0,
            "Klobuchar": 0,
            "Patrick": 0,
            "Sanders": 33,
            "Steyer": 0,
            "Warren": 0,
            "Yang": 0,
            "Other": 0,
            "Uncommitted": 0
        },
        "Final Vote Increase": 1
    },
    {
        "County": "Clay",
        "Precinct": "Waterford-Lone Tree",
        "First Expression": {
            "Bennet": 0,
            "Biden": 6,
            "Bloomberg": 0,
            "Buttigieg": 2,
            "Delaney": 0,
            "Gabbard": 0,
            "Klobuchar": 2,
            "Patrick": 0,
            "Sanders": 0,
            "Steyer": 0,
            "Warren": 2,
            "Yang": 0,
            "Other": 0,
            "Uncommitted": 0
        },
        "Final Expression": {
            "Bennet": 0,
            "Biden": 6,
            "Bloomberg": 0,
            "Buttigieg": 2,
            "Delaney": 0,
            "Gabbard": 0,
            "Klobuchar": 2,
            "Patrick": 0,
            "Sanders": 0,
            "Steyer": 0,
            "Warren": 3,
            "Yang": 0,
            "Other": 0,
            "Uncommitted": 0
        },
        "Final Vote Increase": 1
    },
    {
        "County": "Polk",
        "Precinct": "DES MOINES-24",
        "First Expression": {
            "Bennet": 0,
            "Biden": 15,
            "Bloomberg": 0,
            "Buttigieg": 16,
            "Delaney": 0,
            "Gabbard": 0,
            "Klobuchar": 8,
            "Patrick": 0,
            "Sanders": 21,
            "Steyer": 0,
            "Warren": 3,
            "Yang": 1,
            "Other": 0,
            "Uncommitted": 4
        },
        "Final Expression": {
            "Bennet": 0,
            "Biden": 15,
            "Bloomberg": 0,
            "Buttigieg": 18,
            "Delaney": 0,
            "Gabbard": 0,
            "Klobuchar": 12,
            "Patrick": 0,
            "Sanders": 24,
            "Steyer": 0,
            "Warren": 0,
            "Yang": 0,
            "Other": 0,
            "Uncommitted": 0
        },
        "Final Vote Increase": 1
    },
    {
        "County": "Davis",
        "Precinct": "Bloomfield Ward 3",
        "First Expression": {
            "Bennet": 0,
            "Biden": 4,
            "Bloomberg": 0,
            "Buttigieg": 2,
            "Delaney": 0,
            "Gabbard": 0,
            "Klobuchar": 4,
            "Patrick": 0,
            "Sanders": 6,
            "Steyer": 0,
            "Warren": 2,
            "Yang": 2,
            "Other": 0,
            "Uncommitted": 0
        },
        "Final Expression": {
            "Bennet": 0,
            "Biden": 5,
            "Bloomberg": 0,
            "Buttigieg": 3,
            "Delaney": 0,
            "Gabbard": 0,
            "Klobuchar": 5,
            "Patrick": 0,
            "Sanders": 6,
            "Steyer": 0,
            "Warren": 1,
            "Yang": 1,
            "Other": 0,
            "Uncommitted": 0
        },
        "Final Vote Increase": 1
    },
    {
        "County": "Fayette",
        "Precinct": "OELWEIN - WARD 1",
        "First Expression": {
            "Bennet": 0,
            "Biden": 18,
            "Bloomberg": 0,
            "Buttigieg": 22,
            "Delaney": 0,
            "Gabbard": 0,
            "Klobuchar": 3,
            "Patrick": 0,
            "Sanders": 6,
            "Steyer": 5,
            "Warren": 13,
            "Yang": 2,
            "Other": 0,
            "Uncommitted": 0
        },
        "Final Expression": {
            "Bennet": 0,
            "Biden": 20,
            "Bloomberg": 0,
            "Buttigieg": 30,
            "Delaney": 0,
            "Gabbard": 0,
            "Klobuchar": 0,
            "Patrick": 0,
            "Sanders": 0,
            "Steyer": 0,
            "Warren": 20,
            "Yang": 0,
            "Other": 0,
            "Uncommitted": 0
        },
        "Final Vote Increase": 1
    },
    {
        "County": "Jasper",
        "Precinct": "Colfax Ward 2",
        "First Expression": {
            "Bennet": 1,
            "Biden": 5,
            "Bloomberg": 0,
            "Buttigieg": 17,
            "Delaney": 0,
            "Gabbard": 0,
            "Klobuchar": 0,
            "Patrick": 0,
            "Sanders": 13,
            "Steyer": 2,
            "Warren": 9,
            "Yang": 1,
            "Other": 0,
            "Uncommitted": 1
        },
        "Final Expression": {
            "Bennet": 0,
            "Biden": 10,
            "Bloomberg": 0,
            "Buttigieg": 18,
            "Delaney": 0,
            "Gabbard": 0,
            "Klobuchar": 0,
            "Patrick": 0,
            "Sanders": 13,
            "Steyer": 0,
            "Warren": 9,
            "Yang": 0,
            "Other": 0,
            "Uncommitted": 0
        },
        "Final Vote Increase": 1
    },
    {
        "County": "Polk",
        "Precinct": "ALTOONA-02",
        "First Expression": {
            "Bennet": 0,
            "Biden": 32,
            "Bloomberg": 0,
            "Buttigieg": 39,
            "Delaney": 0,
            "Gabbard": 0,
            "Klobuchar": 29,
            "Patrick": 0,
            "Sanders": 59,
            "Steyer": 0,
            "Warren": 34,
            "Yang": 7,
            "Other": 0,
            "Uncommitted": 0
        },
        "Final Expression": {
            "Bennet": 0,
            "Biden": 32,
            "Bloomberg": 0,
            "Buttigieg": 42,
            "Delaney": 0,
            "Gabbard": 0,
            "Klobuchar": 31,
            "Patrick": 0,
            "Sanders": 61,
            "Steyer": 0,
            "Warren": 35,
            "Yang": 0,
            "Other": 0,
            "Uncommitted": 0
        },
        "Final Vote Increase": 1
    },
    {
        "County": "Linn",
        "Precinct": "Cedar Rapids 25",
        "First Expression": {
            "Bennet": 0,
            "Biden": 69,
            "Bloomberg": 2,
            "Buttigieg": 110,
            "Delaney": 0,
            "Gabbard": 0,
            "Klobuchar": 78,
            "Patrick": 0,
            "Sanders": 78,
            "Steyer": 0,
            "Warren": 82,
            "Yang": 13,
            "Other": 1,
            "Uncommitted": 2
        },
        "Final Expression": {
            "Bennet": 0,
            "Biden": 73,
            "Bloomberg": 0,
            "Buttigieg": 115,
            "Delaney": 0,
            "Gabbard": 0,
            "Klobuchar": 80,
            "Patrick": 0,
            "Sanders": 80,
            "Steyer": 0,
            "Warren": 86,
            "Yang": 0,
            "Other": 0,
            "Uncommitted": 2
        },
        "Final Vote Increase": 1
    },
    {
        "County": "Linn",
        "Precinct": "Cedar Rapids 31",
        "First Expression": {
            "Bennet": 0,
            "Biden": 50,
            "Bloomberg": 0,
            "Buttigieg": 74,
            "Delaney": 0,
            "Gabbard": 1,
            "Klobuchar": 38,
            "Patrick": 0,
            "Sanders": 52,
            "Steyer": 3,
            "Warren": 53,
            "Yang": 5,
            "Other": 0,
            "Uncommitted": 5
        },
        "Final Expression": {
            "Bennet": 0,
            "Biden": 62,
            "Bloomberg": 0,
            "Buttigieg": 88,
            "Delaney": 0,
            "Gabbard": 0,
            "Klobuchar": 0,
            "Patrick": 0,
            "Sanders": 67,
            "Steyer": 0,
            "Warren": 65,
            "Yang": 0,
            "Other": 0,
            "Uncommitted": 0
        },
        "Final Vote Increase": 1
    }
]